wrm3_term_colors/__init__.py
wrm3_term_colors/cls.py
wrm3_term_colors/main.py
wrm3_term_colors/pallette.py
wrm3_term_colors-0.1.2.dist-info/LICENSE
wrm3_term_colors-0.1.2.dist-info/METADATA
wrm3_term_colors-0.1.2.dist-info/WHEEL
wrm3_term_colors-0.1.2.dist-info/top_level.txt
wrm3_term_colors-0.1.2.dist-info/RECORD
