Metadata-Version: 2.1
Name: wrm3_term_colors
Version: 0.1.2
Summary: A terminal printing library that adds more color options.
Home-page: https://github.com/wrm3/wrm3_term_colors.git
Author: WRM3
Author-email: wrm3 <wrmartel3@gmail.com>
License: MIT License
Project-URL: Homepage, https://github.com/wrm3/wrm3_term_colors
Project-URL: Bug Tracker, https://github.com/wrm3/wrm3_term_colors/issues
Classifier: Programming Language :: Python :: 3
Classifier: License :: OSI Approved :: MIT License
Classifier: Operating System :: OS Independent
Requires-Python: >=3.7
License-File: LICENSE
